user_auth_zxw/__init__.py
user_auth_zxw/config.py
user_auth_zxw/main.py
user_auth_zxw/SDK_jwt/__init__.py
user_auth_zxw/SDK_jwt/demo.py
user_auth_zxw/SDK_jwt/jwt.py
user_auth_zxw/SDK_jwt/jwt_刷新管理.py
user_auth_zxw/SDK_jwt/apis/__init__.py
user_auth_zxw/SDK_jwt/apis/api_刷新token.py
user_auth_zxw/SDK_jwt/db_model/__init__.py
user_auth_zxw/SDK_jwt/db_model/model.py
user_auth_zxw/apis/__init__.py
user_auth_zxw/apis/api_JWT.py
user_auth_zxw/apis/api_用户权限_增加.py
user_auth_zxw/apis/api_用户权限_验证.py
user_auth_zxw/apis/schemas.py
user_auth_zxw/apis/api_登录注册/__init__.py
user_auth_zxw/apis/api_登录注册/login.py
user_auth_zxw/apis/api_登录注册/logout.py
user_auth_zxw/apis/api_登录注册/微信H5快捷登录/__init__.py
user_auth_zxw/apis/api_登录注册/微信H5快捷登录/api_注册登录.py
user_auth_zxw/apis/api_登录注册/手机注册登录/__init__.py
user_auth_zxw/apis/api_登录注册/手机注册登录/api_注册登录.py
user_auth_zxw/apis/api_登录注册/手机注册登录/测试短信验证码.py
user_auth_zxw/apis/api_登录注册/账号密码注册登录/__init__.py
user_auth_zxw/apis/api_登录注册/账号密码注册登录/api_注册登录.py
user_auth_zxw/db/__init__.py
user_auth_zxw/db/get_db.py
user_auth_zxw/db/models.py
user_auth_zxw/tests/__init__.py
user_auth_zxw/tests/test_apis.py
user_auth_zxw/tests/test_权限.py
user_auth_zxw/tools/__init__.py
user_auth_zxw/tools/check_sms_code.py
user_auth_zxw/tools/http_exception.py
user_auth_zxw/uniapp_page/手机号注册登录/api_after_register.ts
user_auth_zxw/uniapp_page/手机号注册登录/apis.ts
user_auth_zxw/uniapp_page/手机号注册登录/login_register.vue
user_auth_zxw-1.0.5.dist-info/METADATA
user_auth_zxw-1.0.5.dist-info/WHEEL
user_auth_zxw-1.0.5.dist-info/top_level.txt
user_auth_zxw-1.0.5.dist-info/RECORD
