Metadata-Version: 2.1
Name: user_auth_zxw
Version: 1.0.5
Summary: 用户权限验证工具包
Home-page: https://github.com/sunshineinwater/
Author: 景募
Author-email: 
Classifier: Programming Language :: Python :: 3.10
Classifier: License :: OSI Approved :: MIT License
Classifier: Operating System :: OS Independent
Requires-Dist: pycryptodome<=3.22.0,>=3.20.0
Requires-Dist: fastapi<0.113,>=0.112.0
Requires-Dist: jose<1.1.0,>=1.0.0
Requires-Dist: aiohttp<3.11.0,>=3.10.5
Requires-Dist: httpx<=0.27.0,>=0.23.3
Requires-Dist: sqlalchemy==2.0.32
Requires-Dist: greenlet==3.0.3
Requires-Dist: databases==0.9.0
Requires-Dist: python-jose==3.3.0
Requires-Dist: passlib==1.7.4
Requires-Dist: asyncpg==0.29.0
Requires-Dist: uvicorn<0.31.0,>=0.30.0
Requires-Dist: python-multipart==0.0.9
Requires-Dist: bcrypt==4.2.0
Requires-Dist: app-tools-zxw>=1.0.71
Requires-Dist: alibabacloud-dysmsapi20170525==3.0.0
Requires-Dist: redis==5.2.0
